<?xml version="1.0" encoding="utf-8" ?>
<dwsync>
<file name="disk.png" server="192.168.1.24:886//majiaying/" local="133426863338476786" remote="133420059600000000" Dst="0" />
<file name="disk.svg" server="192.168.1.24:886//majiaying/" local="133426863338476786" remote="133420059600000000" Dst="0" />
<file name="diskwin.png" server="192.168.1.24:886//majiaying/" local="133426863338476786" remote="133420059600000000" Dst="0" />
<file name="diskwin.svg" server="192.168.1.24:886//majiaying/" local="133426863338505082" remote="133420059600000000" Dst="0" />
<file name="folder.svg" server="192.168.1.24:886//majiaying/" local="133426863338514473" remote="133420059600000000" Dst="0" />
<file name="folder.png" server="192.168.1.24:886//majiaying/" local="133426863338514473" remote="133420059600000000" Dst="0" />
<file name="od.png" server="192.168.1.24:886//majiaying/" local="133426863338534444" remote="133420059600000000" Dst="0" />
<file name="qa.png" server="192.168.1.24:886//majiaying/" local="133426863338544417" remote="133420059600000000" Dst="0" />
<file name="rb.png" server="192.168.1.24:886//majiaying/" local="133426863338544417" remote="133420059600000000" Dst="0" />
<file name="thispc.png" server="192.168.1.24:886//majiaying/" local="133426863338554387" remote="133420059600000000" Dst="0" />
<file name="thispc.svg" server="192.168.1.24:886//majiaying/" local="133426863338772810" remote="133420059600000000" Dst="0" />
<file name="tool-copy.png" server="192.168.1.24:886//majiaying/" local="133426863338772810" remote="133420059600000000" Dst="0" />
<file name="tool-cut.png" server="192.168.1.24:886//majiaying/" local="133426863338772810" remote="133420059600000000" Dst="0" />
<file name="tool-new.png" server="192.168.1.24:886//majiaying/" local="133426863338792304" remote="133420059600000000" Dst="0" />
<file name="tool-paste.png" server="192.168.1.24:886//majiaying/" local="133426863338802316" remote="133420059600000000" Dst="0" />
<file name="tool-rename.png" server="192.168.1.24:886//majiaying/" local="133426863338812320" remote="133420059600000000" Dst="0" />
<file name="tool-sort.png" server="192.168.1.24:886//majiaying/" local="133426863338812320" remote="133420059600000000" Dst="0" />
<file name="tool-view.png" server="192.168.1.24:886//majiaying/" local="133426863338812320" remote="133420059600000000" Dst="0" />
<file name="disk.png" server="192.168.1.24:886/majiaying/" local="133426863338476786" remote="133434696000000000" Dst="0" />
<file name="disk.svg" server="192.168.1.24:886/majiaying/" local="133426863338476786" remote="133434696000000000" Dst="0" />
<file name="diskwin.png" server="192.168.1.24:886/majiaying/" local="133426863338476786" remote="133434696000000000" Dst="0" />
<file name="diskwin.svg" server="192.168.1.24:886/majiaying/" local="133426863338505082" remote="133434696000000000" Dst="0" />
<file name="folder.svg" server="192.168.1.24:886/majiaying/" local="133426863338514473" remote="133434696000000000" Dst="0" />
<file name="folder.png" server="192.168.1.24:886/majiaying/" local="133426863338514473" remote="133434696000000000" Dst="0" />
<file name="od.png" server="192.168.1.24:886/majiaying/" local="133426863338534444" remote="133434696000000000" Dst="0" />
<file name="qa.png" server="192.168.1.24:886/majiaying/" local="133426863338544417" remote="133434696000000000" Dst="0" />
<file name="rb.png" server="192.168.1.24:886/majiaying/" local="133426863338544417" remote="133434696000000000" Dst="0" />
<file name="thispc.png" server="192.168.1.24:886/majiaying/" local="133426863338554387" remote="133434696000000000" Dst="0" />
<file name="thispc.svg" server="192.168.1.24:886/majiaying/" local="133426863338772810" remote="133434696000000000" Dst="0" />
<file name="tool-copy.png" server="192.168.1.24:886/majiaying/" local="133426863338772810" remote="133434696000000000" Dst="0" />
<file name="tool-cut.png" server="192.168.1.24:886/majiaying/" local="133426863338772810" remote="133434696000000000" Dst="0" />
<file name="tool-new.png" server="192.168.1.24:886/majiaying/" local="133426863338792304" remote="133434696000000000" Dst="0" />
<file name="tool-paste.png" server="192.168.1.24:886/majiaying/" local="133426863338802316" remote="133434696000000000" Dst="0" />
<file name="tool-rename.png" server="192.168.1.24:886/majiaying/" local="133426863338812320" remote="133434696000000000" Dst="0" />
<file name="tool-sort.png" server="192.168.1.24:886/majiaying/" local="133426863338812320" remote="133434696000000000" Dst="0" />
<file name="tool-view.png" server="192.168.1.24:886/majiaying/" local="133426863338812320" remote="133434696000000000" Dst="0" />
</dwsync>